beards_analytics/__init__.py
beards_analytics/cloud_functions/__init__.py
beards_analytics/cloud_functions/http.py
beards_analytics/common/__init__.py
beards_analytics/common/date.py
beards_analytics/common/logger.py
beards_analytics/common/tasks.py
beards_analytics/common/types.py
beards_analytics/data/__init__.py
beards_analytics/data/models.py
beards_analytics/data/operations.py
beards_analytics/public_api/__init__.py
beards_analytics/public_api/_metadata.py
beards_analytics/public_api/client.py
beards_analytics/public_api/models.py
beards_analytics-2.0.1.dist-info/LICENCE.txt
beards_analytics-2.0.1.dist-info/METADATA
beards_analytics-2.0.1.dist-info/WHEEL
beards_analytics-2.0.1.dist-info/top_level.txt
beards_analytics-2.0.1.dist-info/RECORD
