Metadata-Version: 2.1
Name: beards-analytics
Version: 2.0.1
Summary: Beards Analytics packages
Home-page: https://beardsanalytics.com
Author: Beards Analytics
Author-email: tz@or.com.ua
Classifier: Programming Language :: Python :: 3
Classifier: License :: OSI Approved :: MIT License
Classifier: Operating System :: OS Independent
Requires-Python: >=3.6
License-File: LICENCE.txt
Requires-Dist: python-slugify (==8.0.1)
Requires-Dist: Flask (==2.2.3)
Requires-Dist: pydantic (==1.10.7)
Requires-Dist: functions-framework (==3.3.0)
Requires-Dist: ujson (==5.7.0)
Requires-Dist: pendulum (==2.1.2)
Requires-Dist: google-auth (==2.17.2)
Requires-Dist: requests (==2.28.2)
